google/type/postal_address_pb2.py
google/type/postal_address_pb2_grpc.py
userwatch/__init__.py
userwatch/userwatch.py
userwatch/userwatch_historian_pb2.py
userwatch/userwatch_historian_pb2_grpc.py
userwatch/userwatch_public_pb2.py
userwatch/userwatch_shadow_pb2.py
userwatch/userwatch_shepherd_pb2.py
userwatch/userwatch_shepherd_pb2_grpc.py
userwatch_python-0.0.6.dist-info/LICENSE.md
userwatch_python-0.0.6.dist-info/METADATA
userwatch_python-0.0.6.dist-info/WHEEL
userwatch_python-0.0.6.dist-info/top_level.txt
userwatch_python-0.0.6.dist-info/RECORD
