Metadata-Version: 2.1
Name: userwatch-python
Version: 0.0.6
Author: Userwatch
Classifier: Programming Language :: Python :: 3
Classifier: License :: OSI Approved :: Apache Software License
Classifier: Operating System :: OS Independent
Requires-Python: >=3.7
License-File: LICENSE.md
Requires-Dist: grpcio (>=1.30)
Requires-Dist: protobuf (>=4.0)
